GenAIRR/__init__.py
GenAIRR/TCR/__init__.py
GenAIRR/TCR/sequence/__init__.py
GenAIRR/TCR/sequence/heavy_chain.py
GenAIRR/TCR/sequence/np_region.py
GenAIRR/TCR/simulation/__init__.py
GenAIRR/TCR/simulation/heavy_chain_sequence_augmentor.py
GenAIRR/TCR/simulation/sequence_augmentor_base.py
GenAIRR/alleles/__init__.py
GenAIRR/alleles/allele.py
GenAIRR/container/SimulationContainer.py
GenAIRR/container/__init__.py
GenAIRR/data/__init__.py
GenAIRR/data/builtin_dataconfigs/HUMAN_IGH_EXTENDED.pkl
GenAIRR/data/builtin_dataconfigs/HUMAN_IGH_OGRDB.pkl
GenAIRR/data/builtin_dataconfigs/HUMAN_IGK_OGRDB.pkl
GenAIRR/data/builtin_dataconfigs/HUMAN_IGL_OGRDB.pkl
GenAIRR/data/builtin_dataconfigs/HUMAN_TCRB_IMGT.pkl
GenAIRR/data/builtin_dataconfigs/__init__.py
GenAIRR/data/mutation_model_parameters/HH_S5F_60_META.pkl
GenAIRR/data/mutation_model_parameters/HH_S5F_META.pkl
GenAIRR/data/mutation_model_parameters/HH_S5F_Opposite_META.pkl
GenAIRR/data/mutation_model_parameters/HKL_S5F_META.pkl
GenAIRR/data/mutation_model_parameters/__init__.py
GenAIRR/dataconfig/__init__.py
GenAIRR/dataconfig/config_info.py
GenAIRR/dataconfig/data_config.py
GenAIRR/dataconfig/enums.py
GenAIRR/dataconfig/make/__init__.py
GenAIRR/dataconfig/make/base_dataconfig_builder.py
GenAIRR/dataconfig/make/custom.py
GenAIRR/dataconfig/make/random.py
GenAIRR/dataconfig/make/auxiliary_builders/__init__.py
GenAIRR/dataconfig/make/auxiliary_builders/correction_map_builder.py
GenAIRR/dataconfig/make/auxiliary_builders/np_markov_chain_builder.py
GenAIRR/dataconfig/make/auxiliary_builders/trimming_proportion_builder.py
GenAIRR/mutation/__init__.py
GenAIRR/mutation/config.py
GenAIRR/mutation/mutation_model.py
GenAIRR/mutation/s5f.py
GenAIRR/mutation/s5f_with_substitutions.py
GenAIRR/mutation/uniform.py
GenAIRR/pipeline/AugmentationPipeline.py
GenAIRR/pipeline/__init__.py
GenAIRR/pipeline/plot_parameters.py
GenAIRR/sequence/__init__.py
GenAIRR/sequence/heavy_chain.py
GenAIRR/sequence/light_chain.py
genairr-0.6.0.dist-info/licenses/LICENSE
genairr-0.6.0.dist-info/METADATA
genairr-0.6.0.dist-info/WHEEL
genairr-0.6.0.dist-info/top_level.txt
genairr-0.6.0.dist-info/RECORD
