Metadata-Version: 2.4
Name: GenAIRR
Version: 0.6.0
Summary: An advanced immunoglobulin sequence simulation suite for benchmarking alignment models and sequence analysis.
Home-page: https://github.com/MuteJester/GenAIRR
Author: Thomas Konstantinovsky & Ayelet Peres
Author-email: thomaskon90@gmail.com
Project-URL: Bug Tracker, https://github.com/MuteJester/GenAIRR/issues
Keywords: immunogenetics,sequence simulation,bioinformatics,alignment benchmarking
Classifier: Development Status :: 3 - Alpha
Classifier: Intended Audience :: Science/Research
Classifier: Topic :: Scientific/Engineering :: Bio-Informatics
Classifier: License :: OSI Approved :: GNU General Public License v3 (GPLv3)
Classifier: Programming Language :: Python :: 3
Classifier: Programming Language :: Python :: 3 :: Only
Classifier: Programming Language :: Python :: 3.9
Classifier: Programming Language :: Python :: 3.10
Classifier: Programming Language :: Python :: 3.11
Requires-Python: >=3.9,<3.13
License-File: LICENSE
Requires-Dist: pandas~=1.5.3
Requires-Dist: numpy~=1.26.4
Requires-Dist: scipy~=1.11.1
Requires-Dist: graphviz~=0.20.3
Requires-Dist: tqdm~=4.67.1
Dynamic: author
Dynamic: author-email
Dynamic: classifier
Dynamic: description
Dynamic: description-content-type
Dynamic: home-page
Dynamic: keywords
Dynamic: license-file
Dynamic: project-url
Dynamic: requires-dist
Dynamic: requires-python
Dynamic: summary
